lilota_django/__init__.py
lilota_django/apps.py
lilota_django/models.py
lilota_django/stores.py
lilota_django/tests.py
lilota_django/migrations/0001_initial.py
lilota_django/migrations/__init__.py
lilota_django-0.0.8.dist-info/LICENSE
lilota_django-0.0.8.dist-info/METADATA
lilota_django-0.0.8.dist-info/WHEEL
lilota_django-0.0.8.dist-info/top_level.txt
lilota_django-0.0.8.dist-info/RECORD
