Metadata-Version: 2.1
Name: lilota-django
Version: 0.0.8
Summary: A lightweight solution for long-running tasks
Author-email: Tobias Rössler <tobiasroessler@gmail.com>
Project-URL: Homepage, https://github.com/tobiasroessler/lilota-django
Project-URL: Issues, https://github.com/tobiasroessler/lilota-django/issues
Classifier: Programming Language :: Python :: 3
Classifier: License :: OSI Approved :: MIT License
Classifier: Operating System :: OS Independent
Classifier: Framework :: Django
Requires-Python: >=3.12
License-File: LICENSE
Requires-Dist: Django >=5.0.6
Requires-Dist: lilota >=0.0.5
